micromez/__init__.py
micromez/inputs.py
micromez/outputs.py
micromez/fonts/__init__.py
micromez/fonts/computer_font.py
micromez/fonts/font_builder.py
micromez/fonts/hand_font.py
micromez/fonts/monochrome.py
micromez/fonts/square_font.py
micromez-0.0.4.dist-info/LICENSE
micromez-0.0.4.dist-info/METADATA
micromez-0.0.4.dist-info/WHEEL
micromez-0.0.4.dist-info/top_level.txt
micromez-0.0.4.dist-info/RECORD
