Metadata-Version: 2.1
Name: micromez
Version: 0.0.4
Summary: Python library for support of 96board mezzanine micromez
Home-page: https://github.com/ukBaz/python-micromez
Author: Barry Byford
Author-email: barry_byford@yahoo.co.uk
Maintainer: Barry Byford
Maintainer-email: barry_byford@yahoo.co.uk
License: MIT
Keywords: 96boards Dragonboard 410c
Platform: UNKNOWN
Classifier: Development Status :: 4 - Beta
Classifier: Intended Audience :: Developers
Classifier: Intended Audience :: Education
Classifier: Topic :: System :: Hardware
Classifier: Topic :: Software Development :: Embedded Systems
Classifier: Topic :: Home Automation
Classifier: Topic :: Education
Classifier: License :: OSI Approved :: MIT License
Classifier: Programming Language :: Python :: 2.7
Classifier: Programming Language :: Python :: 3
Provides-Extra: dev
Requires-Dist: bumpversion ; extra == 'dev'
Requires-Dist: twine ; extra == 'dev'
Requires-Dist: wheel ; extra == 'dev'
Requires-Dist: setuptools ; extra == 'dev'
Requires-Dist: sphinx ; extra == 'dev'
Requires-Dist: sphinx-rtd-theme ; extra == 'dev'
Requires-Dist: coverage ; extra == 'dev'
Requires-Dist: pycodestyle ; extra == 'dev'
Requires-Dist: freetype-py ; extra == 'dev'
Provides-Extra: docs
Requires-Dist: sphinx ; extra == 'docs'
Requires-Dist: sphinx-rtd-theme ; extra == 'docs'
Provides-Extra: rel
Requires-Dist: bumpversion ; extra == 'rel'
Requires-Dist: twine ; extra == 'rel'
Requires-Dist: wheel ; extra == 'rel'
Requires-Dist: setuptools ; extra == 'rel'
Provides-Extra: test
Requires-Dist: coverage ; extra == 'test'
Requires-Dist: pycodestyle ; extra == 'test'
